kjsonForPython/__init__.py
kjsonForPython/main.py
kjsonForPython/typeMap.py
kjsonForPython-1.0.0.dist-info/LICENSE
kjsonForPython-1.0.0.dist-info/METADATA
kjsonForPython-1.0.0.dist-info/WHEEL
kjsonForPython-1.0.0.dist-info/top_level.txt
kjsonForPython-1.0.0.dist-info/RECORD
