Metadata-Version: 2.1
Name: kjsonForPython
Version: 1.0.0
Summary: A json library for python, which can be used in network communication
Home-page: https://github.com/kuankuan2007/kjson-for-python/
Author: kuankuan
Author-email: 2163826131@qq.com
License: Mulan PSL v2
Keywords: kjson,json,javascript,network
Platform: windows
Platform: linux
Platform: macos
Classifier: Natural Language :: English
Classifier: Development Status :: 4 - Beta
Classifier: Intended Audience :: Developers
Classifier: Programming Language :: Python :: 3
Classifier: Operating System :: MacOS
Classifier: Operating System :: POSIX :: Linux
Classifier: Operating System :: Microsoft :: Windows
Classifier: License :: OSI Approved :: Mulan Permissive Software License v2 (MulanPSL-2.0)
License-File: LICENSE
